{
  "customer": [
    {
      "stt": 1,
      "addr": "abc",
      "name": "trung",
      "sdt": "06545645456",
      "note": "ábasnsbd",
      "state": "đã định vị",
      "iat": 1542707149
    },
    {
      "stt": 2,
      "addr": "227 Nguyễn Văn Cừ TP Hồ Chí Minh",
      "name": "trung",
      "sdt": "06545645456",
      "note": "ábasnsbd",
      "state": "đã định vị",
      "iat": 1542707360
    },
    {
      "stt": 3,
      "addr": "CHợ Bến Thành",
      "name": "Tuấn",
      "sdt": "065456",
      "note": "ehivoo",
      "state": "đã nhận xe",
      "iat": 1542702358
    },
    {
      "stt": 4,
      "addr": "AGR",
      "name": "ThanhA",
      "sdt": "325",
      "note": "SGDSH",
      "state": "đang di chuyển",
      "iat": 1542786540
    },
    {
      "stt": 6,
      "addr": "AGR",
      "name": "ThanhD",
      "sdt": "325",
      "note": "SGDSH",
      "state": "chưa được định vị",
      "iat": 1542786574
    }
  ]
}